prcop/__init__.py
prcop/alerts.py
prcop/business_hours.py
prcop/checker.py
prcop/cli.py
prcop/config.py
prcop/exceptions.py
prcop/http_client.py
prcop/reporters.py
prcop-0.4.0.dist-info/entry_points.txt
prcop-0.4.0.dist-info/LICENSE
prcop-0.4.0.dist-info/WHEEL
prcop-0.4.0.dist-info/METADATA
prcop-0.4.0.dist-info/RECORD
